opencv_python_rolling-5.0.0.20221015.dist-info/RECORD
opencv_python_rolling-5.0.0.20221015.dist-info/WHEEL
opencv_python_rolling-5.0.0.20221015.dist-info/LICENSE-3RD-PARTY.txt
opencv_python_rolling-5.0.0.20221015.dist-info/top_level.txt
opencv_python_rolling-5.0.0.20221015.dist-info/LICENSE.txt
opencv_python_rolling-5.0.0.20221015.dist-info/METADATA
cv2/config.py
cv2/version.py
cv2/__init__.py
cv2/LICENSE-3RD-PARTY.txt
cv2/load_config_py3.py
cv2/config-3.py
cv2/load_config_py2.py
cv2/LICENSE.txt
cv2/cv2.abi3.so
cv2/misc/version.py
cv2/misc/__init__.py
cv2/mat_wrapper/__init__.py
cv2/gapi/__init__.py
cv2/utils/__init__.py
cv2/.dylibs/libtheoraenc.1.dylib
cv2/.dylibs/libvpx.7.dylib
cv2/.dylibs/libswscale.5.9.100.dylib
cv2/.dylibs/libnettle.8.5.dylib
cv2/.dylibs/libp11-kit.0.dylib
cv2/.dylibs/libhogweed.6.5.dylib
cv2/.dylibs/libvmaf.1.dylib
cv2/.dylibs/libffi.8.dylib
cv2/.dylibs/libvorbisenc.2.dylib
cv2/.dylibs/libavutil.56.70.100.dylib
cv2/.dylibs/libgnutls.30.dylib
cv2/.dylibs/libx264.164.dylib
cv2/.dylibs/libtasn1.6.dylib
cv2/.dylibs/libsoxr.0.1.2.dylib
cv2/.dylibs/libidn2.0.dylib
cv2/.dylibs/libcjson.1.7.15.dylib
cv2/.dylibs/libtheoradec.1.dylib
cv2/.dylibs/libpng16.16.dylib
cv2/.dylibs/libssl.1.1.dylib
cv2/.dylibs/libavformat.58.76.100.dylib
cv2/.dylibs/libswresample.3.9.100.dylib
cv2/.dylibs/libmp3lame.0.dylib
cv2/.dylibs/libdav1d.6.dylib
cv2/.dylibs/libfreetype.6.dylib
cv2/.dylibs/libbrotlienc.1.0.9.dylib
cv2/.dylibs/libx265.199.dylib
cv2/.dylibs/libsodium.23.dylib
cv2/.dylibs/libopencore-amrnb.0.dylib
cv2/.dylibs/librist.4.dylib
cv2/.dylibs/libsrt.1.5.0.dylib
cv2/.dylibs/libintl.8.dylib
cv2/.dylibs/libwebp.7.dylib
cv2/.dylibs/libmbedcrypto.3.2.1.dylib
cv2/.dylibs/librav1e.0.5.1.dylib
cv2/.dylibs/libfontconfig.1.dylib
cv2/.dylibs/libaom.3.4.0.dylib
cv2/.dylibs/libwebpmux.3.dylib
cv2/.dylibs/libvorbis.0.dylib
cv2/.dylibs/libopenjp2.2.5.0.dylib
cv2/.dylibs/libunistring.2.dylib
cv2/.dylibs/liblzma.5.dylib
cv2/.dylibs/libavcodec.58.134.100.dylib
cv2/.dylibs/libavresample.4.0.0.dylib
cv2/.dylibs/libbrotlidec.1.0.9.dylib
cv2/.dylibs/libzmq.5.dylib
cv2/.dylibs/libspeex.1.dylib
cv2/.dylibs/libbrotlicommon.1.0.9.dylib
cv2/.dylibs/libcrypto.1.1.dylib
cv2/.dylibs/libsnappy.1.1.9.dylib
cv2/.dylibs/libopencore-amrwb.0.dylib
cv2/.dylibs/libbluray.2.dylib
