Metadata-Version: 2.1
Name: opencv-python-rolling
Version: 5.0.0.20221015
Summary: Wrapper package for OpenCV python bindings.
Home-page: https://github.com/opencv/opencv-python
Maintainer: OpenCV Team
License: MIT
Platform: UNKNOWN
Classifier: Development Status :: 5 - Production/Stable
Classifier: Environment :: Console
Classifier: Intended Audience :: Developers
Classifier: Intended Audience :: Education
Classifier: Intended Audience :: Information Technology
Classifier: Intended Audience :: Science/Research
Classifier: License :: OSI Approved :: MIT License
Classifier: Operating System :: MacOS
Classifier: Operating System :: Microsoft :: Windows
Classifier: Operating System :: POSIX
Classifier: Operating System :: Unix
Classifier: Programming Language :: Python
Classifier: Programming Language :: Python :: 3
Classifier: Programming Language :: Python :: 3 :: Only
Classifier: Programming Language :: Python :: 3.6
Classifier: Programming Language :: Python :: 3.7
Classifier: Programming Language :: Python :: 3.8
Classifier: Programming Language :: Python :: 3.9
Classifier: Programming Language :: Python :: 3.10
Classifier: Programming Language :: C++
Classifier: Programming Language :: Python :: Implementation :: CPython
Classifier: Topic :: Scientific/Engineering
Classifier: Topic :: Scientific/Engineering :: Image Recognition
Classifier: Topic :: Software Development
Requires-Python: >=3.6
License-File: LICENSE-3RD-PARTY.txt
License-File: LICENSE.txt
Requires-Dist: numpy (>=1.13.3) ; python_version < "3.7"
Requires-Dist: numpy (>=1.21.0) ; python_version <= "3.9" and platform_system == "Darwin" and platform_machine == "arm64"
Requires-Dist: numpy (>=1.21.2) ; python_version >= "3.10"
Requires-Dist: numpy (>=1.21.4) ; python_version >= "3.10" and platform_system == "Darwin"
Requires-Dist: numpy (>=1.19.3) ; python_version >= "3.6" and platform_system == "Linux" and platform_machine == "aarch64"
Requires-Dist: numpy (>=1.14.5) ; python_version >= "3.7"
Requires-Dist: numpy (>=1.17.3) ; python_version >= "3.8"
Requires-Dist: numpy (>=1.19.3) ; python_version >= "3.9"
